cipherbyte.py
cipherbyte-0.1.4.dist-info/METADATA
cipherbyte-0.1.4.dist-info/WHEEL
cipherbyte-0.1.4.dist-info/top_level.txt
cipherbyte-0.1.4.dist-info/RECORD
