Metadata-Version: 2.1
Name: cipherbyte
Version: 0.1.4
Summary: Decrypt python data.
Home-page: https://github.com/walidname113
Author: Kiyatsuka
Author-email: saglotuspetrovih33@gmail.com
License: MIT
Platform: UNKNOWN
Classifier: Programming Language :: Python :: 3
Classifier: License :: OSI Approved :: MIT License
Classifier: Operating System :: OS Independent
Requires-Python: >=3.6
